withrepo/__init__.py
withrepo/constants.py
withrepo/download.py
withrepo/utils.py
withrepo/withrepo.py
withrepo/resources/__init__.py
withrepo/resources/languages.py
withrepo/resources/tree_sitter.py
withrepo/resources/vendor.py
withrepo-0.2.4.dist-info/METADATA
withrepo-0.2.4.dist-info/WHEEL
withrepo-0.2.4.dist-info/licenses/LICENSE
withrepo-0.2.4.dist-info/RECORD
