Metadata-Version: 2.4
Name: withrepo
Version: 0.2.4
Summary: Pythonic access to git repositories
Project-URL: repository, https://github.com/themichaelusa/withrepo
Author-email: Michael Usachenko <michael@useadrenaline.com>
Maintainer-email: Michael Usachenko <michael@useadrenaline.com>
License: MIT License
License-File: LICENSE
Classifier: Development Status :: 4 - Beta
Classifier: Programming Language :: Python
Requires-Python: >=3.10
Requires-Dist: httpx[http2]>=0.28.1
